passwork_api-0.3.0.dist-info/METADATA
passwork_api-0.3.0.dist-info/WHEEL
passwork_api-0.3.0.dist-info/entry_points.txt
passwork_api/__init__.py
passwork_api/models/__init__.py
passwork_api/models/folder.py
passwork_api/models/password.py
passwork_api/models/path.py
passwork_api/passwork_api.py
passwork_api-0.3.0.dist-info/RECORD
